{
  "蔚来|es6|2024": {
    "body_style": "suv",
    "doors": 5,
    "has_sunroof": true,
    "has_roof_rack": false,
    "headlight_layout": "split",
    "rear_door_type": "tailgate",
    "notes": "中型纯电SUV，分体式大灯，全景天幕，隐藏式门把手"
  },
  "蔚来|es8|2024": {
    "body_style": "suv",
    "doors": 5,
    "has_sunroof": true,
    "has_roof_rack": false,
    "headlight_layout": "split",
    "rear_door_type": "tailgate",
    "notes": "中大型纯电SUV，分体式大灯，全景天幕，无行李架"
  },
  "蔚来|et5|2024": {
    "body_style": "sedan",
    "doors": 4,
    "has_sunroof": true,
    "has_roof_rack": false,
    "headlight_layout": "split",
    "rear_door_type": "trunk_lid",
    "notes": "中型纯电轿车，分体式大灯，全景天幕，溜背造型"
  },
  "蔚来|et7|2024": {
    "body_style": "sedan",
    "doors": 4,
    "has_sunroof": true,
    "has_roof_rack": false,
    "headlight_layout": "split",
    "rear_door_type": "trunk_lid",
    "notes": "中大型纯电轿车，分体式大灯，全景天幕，行政级轿车"
  },
  "蔚来|ec6|2024": {
    "body_style": "suv",
    "doors": 5,
    "has_sunroof": true,
    "has_roof_rack": false,
    "headlight_layout": "split",
    "rear_door_type": "tailgate",
    "notes": "中型纯电轿跑SUV，分体式大灯，溜背尾门，全景天幕"
  },
  "理想|l7|2024": {
    "body_style": "suv",
    "doors": 5,
    "has_sunroof": true,
    "has_roof_rack": false,
    "headlight_layout": "贯穿式",
    "rear_door_type": "tailgate",
    "notes": "中大型五座SUV，星环灯贯穿前脸，全景天幕，电动尾门"
  },
  "理想|l8|2024": {
    "body_style": "suv",
    "doors": 5,
    "has_sunroof": true,
    "has_roof_rack": false,
    "headlight_layout": "贯穿式",
    "rear_door_type": "tailgate",
    "notes": "中大型六座SUV，星环灯贯穿前脸，双全景天幕，电动尾门"
  },
  "理想|l9|2024": {
    "body_style": "suv",
    "doors": 5,
    "has_sunroof": true,
    "has_roof_rack": false,
    "headlight_layout": "贯穿式",
    "rear_door_type": "tailgate",
    "notes": "全尺寸六座SUV，星环灯贯穿前脸，前后双全景天幕，电动尾门"
  },
  "理想|mega|2024": {
    "body_style": "mpv",
    "doors": 5,
    "has_sunroof": true,
    "has_roof_rack": false,
    "headlight_layout": "贯穿式",
    "rear_door_type": "sliding",
    "notes": "纯电旗舰MPV，水滴型外观设计，双侧滑门，电动尾门"
  },
  "小鹏|p7|2024": {
    "body_style": "sedan",
    "doors": 4,
    "has_sunroof": true,
    "has_roof_rack": false,
    "headlight_layout": "separate",
    "rear_door_type": "trunk_lid",
    "notes": "中型纯电轿跑，贯穿式前后灯，全景天幕，无框车门"
  },
  "小鹏|g6|2024": {
    "body_style": "suv",
    "doors": 5,
    "has_sunroof": true,
    "has_roof_rack": false,
    "headlight_layout": "separate",
    "rear_door_type": "tailgate",
    "notes": "中型纯电轿跑SUV，溜背造型，电动尾门，全景天幕"
  },
  "小鹏|g9|2024": {
    "body_style": "suv",
    "doors": 5,
    "has_sunroof": true,
    "has_roof_rack": false,
    "headlight_layout": "separate",
    "rear_door_type": "tailgate",
    "notes": "中大型纯电SUV，贯穿式前后灯，全景天幕，电动尾门"
  },
  "小鹏|x9|2024": {
    "body_style": "mpv",
    "doors": 5,
    "has_sunroof": true,
    "has_roof_rack": false,
    "headlight_layout": "separate",
    "rear_door_type": "sliding",
    "notes": "纯电旗舰MPV，星舰造型，双侧滑门，电动尾门，全景天幕"
  },
  "比亚迪|秦plus|2024": {
    "body_style": "sedan",
    "doors": 4,
    "has_sunroof": true,
    "has_roof_rack": false,
    "headlight_layout": "separate",
    "rear_door_type": "trunk_lid",
    "notes": "紧凑型插混/纯电轿车，Dragon Face前脸，普通天窗"
  },
  "比亚迪|秦l|2024": {
    "body_style": "sedan",
    "doors": 4,
    "has_sunroof": true,
    "has_roof_rack": false,
    "headlight_layout": "separate",
    "rear_door_type": "trunk_lid",
    "notes": "中型插混轿车，新一代Dragon Face前脸，贯穿尾灯，全景天幕"
  },
  "比亚迪|汉|2024": {
    "body_style": "sedan",
    "doors": 4,
    "has_sunroof": true,
    "has_roof_rack": false,
    "headlight_layout": "separate",
    "rear_door_type": "trunk_lid",
    "notes": "中大型纯电/插混轿车，Dragon Face前脸，贯穿尾灯，全景天幕"
  },
  "比亚迪|汉l|2024": {
    "body_style": "sedan",
    "doors": 4,
    "has_sunroof": true,
    "has_roof_rack": false,
    "headlight_layout": "separate",
    "rear_door_type": "trunk_lid",
    "notes": "中大型纯电轿车，新一代龙颜设计，贯穿尾灯，全景天幕"
  },
  "比亚迪|海豹|2024": {
    "body_style": "sedan",
    "doors": 4,
    "has_sunroof": true,
    "has_roof_rack": false,
    "headlight_layout": "separate",
    "rear_door_type": "trunk_lid",
    "notes": "中型纯电轿跑，海洋美学设计，溜背造型，全景天幕"
  },
  "比亚迪|唐|2024": {
    "body_style": "suv",
    "doors": 5,
    "has_sunroof": true,
    "has_roof_rack": false,
    "headlight_layout": "separate",
    "rear_door_type": "tailgate",
    "notes": "中大型七座SUV，Dragon Face前脸，电动尾门，全景天幕"
  },
  "比亚迪|宋pro|2024": {
    "body_style": "suv",
    "doors": 5,
    "has_sunroof": true,
    "has_roof_rack": false,
    "headlight_layout": "separate",
    "rear_door_type": "tailgate",
    "notes": "紧凑型SUV，Dragon Face前脸，电动尾门，普通天窗"
  },
  "比亚迪|宋plus|2024": {
    "body_style": "suv",
    "doors": 5,
    "has_sunroof": true,
    "has_roof_rack": false,
    "headlight_layout": "separate",
    "rear_door_type": "tailgate",
    "notes": "紧凑型SUV，海洋美学前脸，电动尾门，全景天幕"
  },
  "比亚迪|元plus|2024": {
    "body_style": "suv",
    "doors": 5,
    "has_sunroof": true,
    "has_roof_rack": false,
    "headlight_layout": "separate",
    "rear_door_type": "tailgate",
    "notes": "紧凑型纯电SUV，Dragon Face前脸，电动尾门，普通天窗"
  },
  "比亚迪|元up|2024": {
    "body_style": "suv",
    "doors": 5,
    "has_sunroof": false,
    "has_roof_rack": false,
    "headlight_layout": "separate",
    "rear_door_type": "tailgate",
    "notes": "小型纯电SUV，海洋美学设计，无天窗，电动尾门"
  },
  "比亚迪|海豚|2024": {
    "body_style": "hatchback",
    "doors": 5,
    "has_sunroof": false,
    "has_roof_rack": false,
    "headlight_layout": "separate",
    "rear_door_type": "tailgate",
    "notes": "小型纯电两厢车，海洋美学设计，无天窗，电动尾门"
  },
  "比亚迪|海鸥|2024": {
    "body_style": "hatchback",
    "doors": 5,
    "has_sunroof": false,
    "has_roof_rack": false,
    "headlight_layout": "separate",
    "rear_door_type": "tailgate",
    "notes": "微型纯电两厢车，海洋美学设计，无天窗，入门级车型"
  },
  "比亚迪|驱逐舰05|2024": {
    "body_style": "sedan",
    "doors": 4,
    "has_sunroof": true,
    "has_roof_rack": false,
    "headlight_layout": "separate",
    "rear_door_type": "trunk_lid",
    "notes": "紧凑型插混轿车，海洋美学前脸，普通天窗，家用轿车"
  },
  "比亚迪|护卫舰07|2024": {
    "body_style": "suv",
    "doors": 5,
    "has_sunroof": true,
    "has_roof_rack": false,
    "headlight_layout": "separate",
    "rear_door_type": "tailgate",
    "notes": "中大型插混SUV，海洋美学前脸，电动尾门，全景天幕"
  },
  "腾势|d9|2024": {
    "body_style": "mpv",
    "doors": 5,
    "has_sunroof": true,
    "has_roof_rack": false,
    "headlight_layout": "贯穿式",
    "rear_door_type": "sliding",
    "notes": "中大型豪华MPV，π-Motion前脸，双侧电动滑门，电动尾门，分段式天窗"
  },
  "仰望|u8|2024": {
    "body_style": "suv",
    "doors": 5,
    "has_sunroof": true,
    "has_roof_rack": true,
    "headlight_layout": "separate",
    "rear_door_type": "tailgate",
    "notes": "大型豪华越野SUV，鼎字大灯设计，行李架，电动尾门，全景天幕"
  },
  "方程豹|豹5|2024": {
    "body_style": "suv",
    "doors": 5,
    "has_sunroof": true,
    "has_roof_rack": true,
    "headlight_layout": "separate",
    "rear_door_type": "tailgate",
    "notes": "中大型越野SUV，硬派方盒子造型，行李架，电动尾门，全景天幕"
  },
  "特斯拉|model 3|2024": {
    "body_style": "sedan",
    "doors": 4,
    "has_sunroof": true,
    "has_roof_rack": false,
    "headlight_layout": "separate",
    "rear_door_type": "trunk_lid",
    "notes": "中型纯电轿车，极简无格栅前脸，全景玻璃车顶，隐藏门把手"
  },
  "特斯拉|model y|2024": {
    "body_style": "suv",
    "doors": 5,
    "has_sunroof": true,
    "has_roof_rack": false,
    "headlight_layout": "separate",
    "rear_door_type": "tailgate",
    "notes": "中型纯电SUV，溜背造型，全景玻璃车顶，电动尾门"
  },
  "特斯拉|model s|2024": {
    "body_style": "sedan",
    "doors": 4,
    "has_sunroof": true,
    "has_roof_rack": false,
    "headlight_layout": "separate",
    "rear_door_type": "trunk_lid",
    "notes": "中大型纯电轿车，极简无格栅前脸，全景玻璃车顶，隐藏门把手"
  },
  "特斯拉|model x|2024": {
    "body_style": "suv",
    "doors": 5,
    "has_sunroof": true,
    "has_roof_rack": false,
    "headlight_layout": "separate",
    "rear_door_type": "tailgate",
    "notes": "中大型纯电SUV，鹰翼门设计，全景玻璃车顶，电动尾门"
  },
  "宝马|3系|2024": {
    "body_style": "sedan",
    "doors": 4,
    "has_sunroof": true,
    "has_roof_rack": false,
    "headlight_layout": "separate",
    "rear_door_type": "trunk_lid",
    "notes": "中型豪华轿车，双肾格栅，天使眼大灯，普通天窗"
  },
  "宝马|5系|2024": {
    "body_style": "sedan",
    "doors": 4,
    "has_sunroof": true,
    "has_roof_rack": false,
    "headlight_layout": "separate",
    "rear_door_type": "trunk_lid",
    "notes": "中大型豪华轿车，双肾格栅，贯穿式尾灯（新款），分段式天窗"
  },
  "宝马|x3|2024": {
    "body_style": "suv",
    "doors": 5,
    "has_sunroof": true,
    "has_roof_rack": true,
    "headlight_layout": "separate",
    "rear_door_type": "tailgate",
    "notes": "中型豪华SUV，双肾格栅，行李架，电动尾门，全景天窗"
  },
  "宝马|x5|2024": {
    "body_style": "suv",
    "doors": 5,
    "has_sunroof": true,
    "has_roof_rack": true,
    "headlight_layout": "separate",
    "rear_door_type": "tailgate",
    "notes": "中大型豪华SUV，双肾格栅，行李架，电动尾门，全景天窗"
  },
  "宝马|4系|2024": {
    "body_style": "coupe",
    "doors": 2,
    "has_sunroof": true,
    "has_roof_rack": false,
    "headlight_layout": "separate",
    "rear_door_type": "trunk_lid",
    "notes": "中型豪华轿跑，大双肾格栅，无框车门，溜背造型，普通天窗"
  },
  "宝马|i3|2024": {
    "body_style": "sedan",
    "doors": 4,
    "has_sunroof": true,
    "has_roof_rack": false,
    "headlight_layout": "separate",
    "rear_door_type": "trunk_lid",
    "notes": "中型纯电轿车，封闭式双肾格栅，天使眼大灯，全景天幕"
  },
  "奔驰|c级|2024": {
    "body_style": "sedan",
    "doors": 4,
    "has_sunroof": true,
    "has_roof_rack": false,
    "headlight_layout": "separate",
    "rear_door_type": "trunk_lid",
    "notes": "中型豪华轿车，夜幕星河格栅，普通天窗，经典三厢造型"
  },
  "奔驰|e级|2024": {
    "body_style": "sedan",
    "doors": 4,
    "has_sunroof": true,
    "has_roof_rack": false,
    "headlight_layout": "separate",
    "rear_door_type": "trunk_lid",
    "notes": "中大型豪华轿车，花生大灯，贯穿尾灯，分段式全景天窗"
  },
  "奔驰|glc|2024": {
    "body_style": "suv",
    "doors": 5,
    "has_sunroof": true,
    "has_roof_rack": true,
    "headlight_layout": "separate",
    "rear_door_type": "tailgate",
    "notes": "中型豪华SUV，夜幕星河格栅，行李架，电动尾门，全景天窗"
  },
  "奔驰|gle|2024": {
    "body_style": "suv",
    "doors": 5,
    "has_sunroof": true,
    "has_roof_rack": true,
    "headlight_layout": "separate",
    "rear_door_type": "tailgate",
    "notes": "中大型豪华SUV，夜幕星河格栅，行李架，电动尾门，全景天窗"
  },
  "奔驰|cle|2024": {
    "body_style": "coupe",
    "doors": 2,
    "has_sunroof": true,
    "has_roof_rack": false,
    "headlight_layout": "separate",
    "rear_door_type": "trunk_lid",
    "notes": "中型豪华轿跑，夜幕星河格栅，无框车门，溜背造型，普通天窗"
  },
  "奔驰|s级|2024": {
    "body_style": "sedan",
    "doors": 4,
    "has_sunroof": true,
    "has_roof_rack": false,
    "headlight_layout": "separate",
    "rear_door_type": "trunk_lid",
    "notes": "大型豪华轿车，盾形格栅，流星雨大灯，分段式全景天窗"
  },
  "奥迪|a4l|2024": {
    "body_style": "sedan",
    "doors": 4,
    "has_sunroof": true,
    "has_roof_rack": false,
    "headlight_layout": "separate",
    "rear_door_type": "trunk_lid",
    "notes": "中型豪华轿车，六边形格栅，矩阵LED大灯，普通天窗"
  },
  "奥迪|a6l|2024": {
    "body_style": "sedan",
    "doors": 4,
    "has_sunroof": true,
    "has_roof_rack": false,
    "headlight_layout": "separate",
    "rear_door_type": "trunk_lid",
    "notes": "中大型豪华轿车，六边形格栅，矩阵LED大灯，分段式全景天窗"
  },
  "奥迪|q5l|2024": {
    "body_style": "suv",
    "doors": 5,
    "has_sunroof": true,
    "has_roof_rack": true,
    "headlight_layout": "separate",
    "rear_door_type": "tailgate",
    "notes": "中型豪华SUV，八边形格栅，行李架，电动尾门，全景天窗"
  },
  "奥迪|a5|2024": {
    "body_style": "coupe",
    "doors": 2,
    "has_sunroof": true,
    "has_roof_rack": false,
    "headlight_layout": "separate",
    "rear_door_type": "trunk_lid",
    "notes": "中型豪华轿跑，六边形格栅，无框车门，溜背造型，普通天窗"
  },
  "奥迪|a4 avant|2024": {
    "body_style": "wagon",
    "doors": 5,
    "has_sunroof": true,
    "has_roof_rack": true,
    "headlight_layout": "separate",
    "rear_door_type": "tailgate",
    "notes": "中型豪华旅行车，六边形格栅，行李架，电动尾门，全景天窗"
  },
  "奥迪|q3|2024": {
    "body_style": "suv",
    "doors": 5,
    "has_sunroof": true,
    "has_roof_rack": true,
    "headlight_layout": "separate",
    "rear_door_type": "tailgate",
    "notes": "紧凑型豪华SUV，八边形格栅，行李架，电动尾门，全景天窗"
  },
  "丰田|凯美瑞|2024": {
    "body_style": "sedan",
    "doors": 4,
    "has_sunroof": true,
    "has_roof_rack": false,
    "headlight_layout": "separate",
    "rear_door_type": "trunk_lid",
    "notes": "中型轿车，梯形大嘴格栅，C型大灯，普通天窗"
  },
  "丰田|卡罗拉|2024": {
    "body_style": "sedan",
    "doors": 4,
    "has_sunroof": false,
    "has_roof_rack": false,
    "headlight_layout": "separate",
    "rear_door_type": "trunk_lid",
    "notes": "紧凑型轿车，梯形格栅，普通大灯，无天窗，家用代步"
  },
  "丰田|雷凌|2024": {
    "body_style": "sedan",
    "doors": 4,
    "has_sunroof": false,
    "has_roof_rack": false,
    "headlight_layout": "separate",
    "rear_door_type": "trunk_lid",
    "notes": "紧凑型轿车，梯形格栅，普通大灯，无天窗，家用代步"
  },
  "丰田|rav4荣放|2024": {
    "body_style": "suv",
    "doors": 5,
    "has_sunroof": true,
    "has_roof_rack": true,
    "headlight_layout": "separate",
    "rear_door_type": "tailgate",
    "notes": "紧凑型SUV，梯形格栅，行李架，电动尾门，全景天窗"
  },
  "丰田|威兰达|2024": {
    "body_style": "suv",
    "doors": 5,
    "has_sunroof": true,
    "has_roof_rack": true,
    "headlight_layout": "separate",
    "rear_door_type": "tailgate",
    "notes": "紧凑型SUV，梯形格栅，行李架，电动尾门，全景天窗"
  },
  "丰田|锋兰达|2024": {
    "body_style": "suv",
    "doors": 5,
    "has_sunroof": false,
    "has_roof_rack": false,
    "headlight_layout": "separate",
    "rear_door_type": "tailgate",
    "notes": "紧凑型SUV，梯形格栅，无行李架，普通天窗，家用SUV"
  },
  "丰田|汉兰达|2024": {
    "body_style": "suv",
    "doors": 5,
    "has_sunroof": true,
    "has_roof_rack": true,
    "headlight_layout": "separate",
    "rear_door_type": "tailgate",
    "notes": "中型七座SUV，梯形格栅，行李架，电动尾门，全景天窗"
  },
  "丰田|赛那|2024": {
    "body_style": "mpv",
    "doors": 5,
    "has_sunroof": true,
    "has_roof_rack": false,
    "headlight_layout": "separate",
    "rear_door_type": "sliding",
    "notes": "中大型MPV，梯形格栅，双侧电动滑门，电动尾门，分段式天窗"
  },
  "丰田|格瑞维亚|2024": {
    "body_style": "mpv",
    "doors": 5,
    "has_sunroof": true,
    "has_roof_rack": false,
    "headlight_layout": "separate",
    "rear_door_type": "sliding",
    "notes": "中大型MPV，梯形格栅，双侧电动滑门，电动尾门，分段式天窗"
  },
  "本田|雅阁|2024": {
    "body_style": "sedan",
    "doors": 4,
    "has_sunroof": true,
    "has_roof_rack": false,
    "headlight_layout": "separate",
    "rear_door_type": "trunk_lid",
    "notes": "中型轿车，六边形格栅，贯穿式尾灯，普通天窗"
  },
  "本田|思域|2024": {
    "body_style": "sedan",
    "doors": 4,
    "has_sunroof": true,
    "has_roof_rack": false,
    "headlight_layout": "separate",
    "rear_door_type": "trunk_lid",
    "notes": "紧凑型轿车，扁平格栅，贯穿式尾灯，普通天窗，运动风格"
  },
  "本田|型格|2024": {
    "body_style": "sedan",
    "doors": 4,
    "has_sunroof": true,
    "has_roof_rack": false,
    "headlight_layout": "separate",
    "rear_door_type": "trunk_lid",
    "notes": "紧凑型轿车，扁平格栅，贯穿式尾灯，普通天窗，运动风格"
  },
  "本田|cr-v|2024": {
    "body_style": "suv",
    "doors": 5,
    "has_sunroof": true,
    "has_roof_rack": true,
    "headlight_layout": "separate",
    "rear_door_type": "tailgate",
    "notes": "紧凑型SUV，六边形格栅，行李架，电动尾门，全景天窗"
  },
  "本田|皓影|2024": {
    "body_style": "suv",
    "doors": 5,
    "has_sunroof": true,
    "has_roof_rack": true,
    "headlight_layout": "separate",
    "rear_door_type": "tailgate",
    "notes": "紧凑型SUV，六边形格栅，行李架，电动尾门，全景天窗"
  },
  "本田|冠道|2024": {
    "body_style": "suv",
    "doors": 5,
    "has_sunroof": true,
    "has_roof_rack": true,
    "headlight_layout": "separate",
    "rear_door_type": "tailgate",
    "notes": "中型SUV，六边形格栅，行李架，电动尾门，全景天窗"
  },
  "本田|ur-v|2024": {
    "body_style": "suv",
    "doors": 5,
    "has_sunroof": true,
    "has_roof_rack": true,
    "headlight_layout": "separate",
    "rear_door_type": "tailgate",
    "notes": "中型SUV，六边形格栅，行李架，电动尾门，全景天窗"
  },
  "本田|奥德赛|2024": {
    "body_style": "mpv",
    "doors": 5,
    "has_sunroof": true,
    "has_roof_rack": false,
    "headlight_layout": "separate",
    "rear_door_type": "sliding",
    "notes": "中型MPV，大嘴格栅，双侧电动滑门，电动尾门，分段式天窗"
  },
  "本田|艾力绅|2024": {
    "body_style": "mpv",
    "doors": 5,
    "has_sunroof": true,
    "has_roof_rack": false,
    "headlight_layout": "separate",
    "rear_door_type": "sliding",
    "notes": "中型MPV，大嘴格栅，双侧电动滑门，电动尾门，分段式天窗"
  },
  "日产|轩逸|2024": {
    "body_style": "sedan",
    "doors": 4,
    "has_sunroof": false,
    "has_roof_rack": false,
    "headlight_layout": "separate",
    "rear_door_type": "trunk_lid",
    "notes": "紧凑型轿车，V-Motion格栅，普通大灯，无天窗，家用代步"
  },
  "日产|天籁|2024": {
    "body_style": "sedan",
    "doors": 4,
    "has_sunroof": true,
    "has_roof_rack": false,
    "headlight_layout": "separate",
    "rear_door_type": "trunk_lid",
    "notes": "中型轿车，V-Motion格栅，普通天窗，家用舒适"
  },
  "日产|奇骏|2024": {
    "body_style": "suv",
    "doors": 5,
    "has_sunroof": true,
    "has_roof_rack": true,
    "headlight_layout": "separate",
    "rear_door_type": "tailgate",
    "notes": "紧凑型SUV，V-Motion格栅，行李架，电动尾门，全景天窗"
  },
  "日产|逍客|2024": {
    "body_style": "suv",
    "doors": 5,
    "has_sunroof": true,
    "has_roof_rack": false,
    "headlight_layout": "separate",
    "rear_door_type": "tailgate",
    "notes": "紧凑型SUV，V-Motion格栅，普通天窗，电动尾门"
  },
  "日产|途乐|2024": {
    "body_style": "suv",
    "doors": 5,
    "has_sunroof": true,
    "has_roof_rack": true,
    "headlight_layout": "separate",
    "rear_door_type": "tailgate",
    "notes": "大型越野SUV，V-Motion格栅，行李架，电动尾门，全景天窗"
  },
  "日产|ariya艾睿雅|2024": {
    "body_style": "suv",
    "doors": 5,
    "has_sunroof": true,
    "has_roof_rack": false,
    "headlight_layout": "separate",
    "rear_door_type": "tailgate",
    "notes": "紧凑型纯电SUV，封闭式盾形格栅，贯穿尾灯，全景天幕"
  },
  "大众|迈腾|2024": {
    "body_style": "sedan",
    "doors": 4,
    "has_sunroof": true,
    "has_roof_rack": false,
    "headlight_layout": "separate",
    "rear_door_type": "trunk_lid",
    "notes": "中型轿车，横幅格栅，贯穿尾灯（新款），普通天窗"
  },
  "大众|帕萨特|2024": {
    "body_style": "sedan",
    "doors": 4,
    "has_sunroof": true,
    "has_roof_rack": false,
    "headlight_layout": "separate",
    "rear_door_type": "trunk_lid",
    "notes": "中型轿车，星空/经典双前脸，贯穿尾灯，普通天窗"
  },
  "大众|朗逸|2024": {
    "body_style": "sedan",
    "doors": 4,
    "has_sunroof": false,
    "has_roof_rack": false,
    "headlight_layout": "separate",
    "rear_door_type": "trunk_lid",
    "notes": "紧凑型轿车，横幅格栅，普通大灯，无天窗，家用代步"
  },
  "大众|速腾|2024": {
    "body_style": "sedan",
    "doors": 4,
    "has_sunroof": true,
    "has_roof_rack": false,
    "headlight_layout": "separate",
    "rear_door_type": "trunk_lid",
    "notes": "紧凑型轿车，横幅格栅，普通天窗，家用代步"
  },
  "大众|宝来|2024": {
    "body_style": "sedan",
    "doors": 4,
    "has_sunroof": false,
    "has_roof_rack": false,
    "headlight_layout": "separate",
    "rear_door_type": "trunk_lid",
    "notes": "紧凑型轿车，横幅格栅，普通大灯，无天窗，家用代步"
  },
  "大众|途观l|2024": {
    "body_style": "suv",
    "doors": 5,
    "has_sunroof": true,
    "has_roof_rack": true,
    "headlight_layout": "separate",
    "rear_door_type": "tailgate",
    "notes": "中型SUV，横幅格栅，行李架，电动尾门，全景天窗"
  },
  "大众|探岳|2024": {
    "body_style": "suv",
    "doors": 5,
    "has_sunroof": true,
    "has_roof_rack": true,
    "headlight_layout": "separate",
    "rear_door_type": "tailgate",
    "notes": "中型SUV，X型前脸，行李架，电动尾门，全景天窗"
  },
  "大众|揽巡|2024": {
    "body_style": "suv",
    "doors": 5,
    "has_sunroof": true,
    "has_roof_rack": true,
    "headlight_layout": "separate",
    "rear_door_type": "tailgate",
    "notes": "中大型SUV，横幅格栅，行李架，电动尾门，全景天窗"
  },
  "大众|途昂|2024": {
    "body_style": "suv",
    "doors": 5,
    "has_sunroof": true,
    "has_roof_rack": true,
    "headlight_layout": "separate",
    "rear_door_type": "tailgate",
    "notes": "中大型SUV，横幅格栅，行李架，电动尾门，全景天窗"
  },
  "大众|id.3|2024": {
    "body_style": "hatchback",
    "doors": 5,
    "has_sunroof": true,
    "has_roof_rack": false,
    "headlight_layout": "separate",
    "rear_door_type": "tailgate",
    "notes": "紧凑型纯电两厢车，封闭式前脸，全景天幕，电动尾门"
  },
  "大众|id.4|2024": {
    "body_style": "suv",
    "doors": 5,
    "has_sunroof": true,
    "has_roof_rack": false,
    "headlight_layout": "separate",
    "rear_door_type": "tailgate",
    "notes": "紧凑型纯电SUV，封闭式前脸，贯穿灯带，全景天幕，电动尾门"
  },
  "别克|君威|2024": {
    "body_style": "sedan",
    "doors": 4,
    "has_sunroof": true,
    "has_roof_rack": false,
    "headlight_layout": "separate",
    "rear_door_type": "trunk_lid",
    "notes": "中型轿车，飞翼格栅，展翼大灯，普通天窗"
  },
  "别克|君越|2024": {
    "body_style": "sedan",
    "doors": 4,
    "has_sunroof": true,
    "has_roof_rack": false,
    "headlight_layout": "separate",
    "rear_door_type": "trunk_lid",
    "notes": "中大型轿车，飞翼格栅，展翼大灯，分段式天窗"
  },
  "别克|昂科威|2024": {
    "body_style": "suv",
    "doors": 5,
    "has_sunroof": true,
    "has_roof_rack": true,
    "headlight_layout": "separate",
    "rear_door_type": "tailgate",
    "notes": "中型SUV，飞翼格栅，行李架，电动尾门，全景天窗"
  },
  "别克|gl8|2024": {
    "body_style": "mpv",
    "doors": 5,
    "has_sunroof": true,
    "has_roof_rack": false,
    "headlight_layout": "separate",
    "rear_door_type": "sliding",
    "notes": "中大型MPV，飞翼格栅，双侧电动滑门，电动尾门，分段式天窗"
  },
  "别克|世纪|2024": {
    "body_style": "mpv",
    "doors": 5,
    "has_sunroof": true,
    "has_roof_rack": false,
    "headlight_layout": "separate",
    "rear_door_type": "sliding",
    "notes": "大型豪华MPV，飞翼格栅，双侧电动滑门，电动尾门，分段式天窗"
  },
  "雪佛兰|科鲁泽|2024": {
    "body_style": "sedan",
    "doors": 4,
    "has_sunroof": false,
    "has_roof_rack": false,
    "headlight_layout": "separate",
    "rear_door_type": "trunk_lid",
    "notes": "紧凑型轿车，双格栅设计，普通大灯，无天窗，家用代步"
  },
  "雪佛兰|迈锐宝xl|2024": {
    "body_style": "sedan",
    "doors": 4,
    "has_sunroof": true,
    "has_roof_rack": false,
    "headlight_layout": "separate",
    "rear_door_type": "trunk_lid",
    "notes": "中型轿车，双格栅设计，普通天窗，溜背造型"
  },
  "雪佛兰|探界者|2024": {
    "body_style": "suv",
    "doors": 5,
    "has_sunroof": true,
    "has_roof_rack": true,
    "headlight_layout": "separate",
    "rear_door_type": "tailgate",
    "notes": "中型SUV，双格栅设计，行李架，电动尾门，全景天窗"
  },
  "雪佛兰|开拓者|2024": {
    "body_style": "suv",
    "doors": 5,
    "has_sunroof": true,
    "has_roof_rack": true,
    "headlight_layout": "separate",
    "rear_door_type": "tailgate",
    "notes": "中大型SUV，双格栅设计，行李架，电动尾门，全景天窗"
  },
  "福特|蒙迪欧|2024": {
    "body_style": "sedan",
    "doors": 4,
    "has_sunroof": true,
    "has_roof_rack": false,
    "headlight_layout": "separate",
    "rear_door_type": "trunk_lid",
    "notes": "中型轿车，八边形格栅，贯穿尾灯，普通天窗"
  },
  "福特|锐界l|2024": {
    "body_style": "suv",
    "doors": 5,
    "has_sunroof": true,
    "has_roof_rack": true,
    "headlight_layout": "separate",
    "rear_door_type": "tailgate",
    "notes": "中型七座SUV，八边形格栅，行李架，电动尾门，全景天窗"
  },
  "福特|探险者|2024": {
    "body_style": "suv",
    "doors": 5,
    "has_sunroof": true,
    "has_roof_rack": true,
    "headlight_layout": "separate",
    "rear_door_type": "tailgate",
    "notes": "中大型SUV，八边形格栅，行李架，电动尾门，全景天窗"
  },
  "福特|mustang mach-e|2024": {
    "body_style": "suv",
    "doors": 5,
    "has_sunroof": true,
    "has_roof_rack": false,
    "headlight_layout": "separate",
    "rear_door_type": "tailgate",
    "notes": "中型纯电轿跑SUV，封闭式 Mustang 前脸，溜背造型，全景天幕"
  },
  "福特|f-150|2024": {
    "body_style": "pickup",
    "doors": 4,
    "has_sunroof": true,
    "has_roof_rack": false,
    "headlight_layout": "separate",
    "rear_door_type": "tailgate",
    "notes": "大型皮卡，C型大灯，货箱尾门，全景天窗，越野风格"
  },
  "现代|伊兰特|2024": {
    "body_style": "sedan",
    "doors": 4,
    "has_sunroof": true,
    "has_roof_rack": false,
    "headlight_layout": "separate",
    "rear_door_type": "trunk_lid",
    "notes": "紧凑型轿车，参数化格栅，贯穿尾灯，普通天窗"
  },
  "现代|索纳塔|2024": {
    "body_style": "sedan",
    "doors": 4,
    "has_sunroof": true,
    "has_roof_rack": false,
    "headlight_layout": "separate",
    "rear_door_type": "trunk_lid",
    "notes": "中型轿车，贯穿灯带，溜背造型，普通天窗"
  },
  "现代|途胜l|2024": {
    "body_style": "suv",
    "doors": 5,
    "has_sunroof": true,
    "has_roof_rack": true,
    "headlight_layout": "separate",
    "rear_door_type": "tailgate",
    "notes": "紧凑型SUV，参数化格栅，行李架，电动尾门，全景天窗"
  },
  "现代|胜达|2024": {
    "body_style": "suv",
    "doors": 5,
    "has_sunroof": true,
    "has_roof_rack": true,
    "headlight_layout": "separate",
    "rear_door_type": "tailgate",
    "notes": "中大型SUV，H型灯带，行李架，电动尾门，全景天窗"
  },
  "起亚|k3|2024": {
    "body_style": "sedan",
    "doors": 4,
    "has_sunroof": false,
    "has_roof_rack": false,
    "headlight_layout": "separate",
    "rear_door_type": "trunk_lid",
    "notes": "紧凑型轿车，虎啸格栅，普通大灯，无天窗，家用代步"
  },
  "起亚|k5|2024": {
    "body_style": "sedan",
    "doors": 4,
    "has_sunroof": true,
    "has_roof_rack": false,
    "headlight_layout": "separate",
    "rear_door_type": "trunk_lid",
    "notes": "中型轿车，虎啸格栅，贯穿尾灯，普通天窗，溜背造型"
  },
  "起亚|狮铂拓界|2024": {
    "body_style": "suv",
    "doors": 5,
    "has_sunroof": true,
    "has_roof_rack": true,
    "headlight_layout": "separate",
    "rear_door_type": "tailgate",
    "notes": "紧凑型SUV，虎啸格栅，行李架，电动尾门，全景天窗"
  },
  "起亚|嘉华|2024": {
    "body_style": "mpv",
    "doors": 5,
    "has_sunroof": true,
    "has_roof_rack": false,
    "headlight_layout": "separate",
    "rear_door_type": "sliding",
    "notes": "中大型MPV，虎啸格栅，双侧电动滑门，电动尾门，分段式天窗"
  },
  "马自达|马自达3 昂克赛拉|2024": {
    "body_style": "sedan",
    "doors": 4,
    "has_sunroof": true,
    "has_roof_rack": false,
    "headlight_layout": "separate",
    "rear_door_type": "trunk_lid",
    "notes": "紧凑型轿车，魂动设计，普通天窗，运动风格"
  },
  "马自达|cx-5|2024": {
    "body_style": "suv",
    "doors": 5,
    "has_sunroof": true,
    "has_roof_rack": true,
    "headlight_layout": "separate",
    "rear_door_type": "tailgate",
    "notes": "紧凑型SUV，魂动设计，行李架，电动尾门，全景天窗"
  },
  "马自达|cx-50|2024": {
    "body_style": "suv",
    "doors": 5,
    "has_sunroof": true,
    "has_roof_rack": true,
    "headlight_layout": "separate",
    "rear_door_type": "tailgate",
    "notes": "紧凑型SUV，魂动设计，行李架，电动尾门，全景天窗"
  },
  "标致|408|2024": {
    "body_style": "sedan",
    "doors": 4,
    "has_sunroof": true,
    "has_roof_rack": false,
    "headlight_layout": "separate",
    "rear_door_type": "trunk_lid",
    "notes": "紧凑型轿车，狮吼前脸，獠牙日行灯，普通天窗"
  },
  "标致|508|2024": {
    "body_style": "sedan",
    "doors": 4,
    "has_sunroof": true,
    "has_roof_rack": false,
    "headlight_layout": "separate",
    "rear_door_type": "trunk_lid",
    "notes": "中型轿车，狮吼前脸，獠牙日行灯，普通天窗，溜背造型"
  },
  "标致|4008|2024": {
    "body_style": "suv",
    "doors": 5,
    "has_sunroof": true,
    "has_roof_rack": true,
    "headlight_layout": "separate",
    "rear_door_type": "tailgate",
    "notes": "紧凑型SUV，狮吼前脸，行李架，电动尾门，全景天窗"
  },
  "标致|5008|2024": {
    "body_style": "suv",
    "doors": 5,
    "has_sunroof": true,
    "has_roof_rack": true,
    "headlight_layout": "separate",
    "rear_door_type": "tailgate",
    "notes": "中型七座SUV，狮吼前脸，行李架，电动尾门，全景天窗"
  },
  "雪铁龙|凡尔赛c5 x|2024": {
    "body_style": "wagon",
    "doors": 5,
    "has_sunroof": true,
    "has_roof_rack": true,
    "headlight_layout": "separate",
    "rear_door_type": "tailgate",
    "notes": "中型跨界旅行车，X型前脸，行李架，电动尾门，全景天窗"
  },
  "雪铁龙|天逸c5 aircross|2024": {
    "body_style": "suv",
    "doors": 5,
    "has_sunroof": true,
    "has_roof_rack": true,
    "headlight_layout": "separate",
    "rear_door_type": "tailgate",
    "notes": "紧凑型SUV，分体式大灯，行李架，电动尾门，全景天窗"
  },
  "斯柯达|明锐|2024": {
    "body_style": "hatchback",
    "doors": 5,
    "has_sunroof": true,
    "has_roof_rack": false,
    "headlight_layout": "separate",
    "rear_door_type": "tailgate",
    "notes": "紧凑型掀背轿车，直瀑格栅，普通天窗，电动尾门"
  },
  "斯柯达|柯迪亚克|2024": {
    "body_style": "suv",
    "doors": 5,
    "has_sunroof": true,
    "has_roof_rack": true,
    "headlight_layout": "separate",
    "rear_door_type": "tailgate",
    "notes": "中型SUV，直瀑格栅，行李架，电动尾门，全景天窗"
  },
  "斯柯达|速派|2024": {
    "body_style": "sedan",
    "doors": 4,
    "has_sunroof": true,
    "has_roof_rack": false,
    "headlight_layout": "separate",
    "rear_door_type": "trunk_lid",
    "notes": "中型轿车，直瀑格栅，普通天窗，掀背尾门"
  },
  "沃尔沃|s60|2024": {
    "body_style": "sedan",
    "doors": 4,
    "has_sunroof": true,
    "has_roof_rack": false,
    "headlight_layout": "separate",
    "rear_door_type": "trunk_lid",
    "notes": "中型豪华轿车，雷神之锤大灯，普通天窗，北欧简约"
  },
  "沃尔沃|s90|2024": {
    "body_style": "sedan",
    "doors": 4,
    "has_sunroof": true,
    "has_roof_rack": false,
    "headlight_layout": "separate",
    "rear_door_type": "trunk_lid",
    "notes": "中大型豪华轿车，雷神之锤大灯，分段式全景天窗，北欧简约"
  },
  "沃尔沃|xc60|2024": {
    "body_style": "suv",
    "doors": 5,
    "has_sunroof": true,
    "has_roof_rack": true,
    "headlight_layout": "separate",
    "rear_door_type": "tailgate",
    "notes": "中型豪华SUV，雷神之锤大灯，行李架，电动尾门，全景天窗"
  },
  "沃尔沃|xc90|2024": {
    "body_style": "suv",
    "doors": 5,
    "has_sunroof": true,
    "has_roof_rack": true,
    "headlight_layout": "separate",
    "rear_door_type": "tailgate",
    "notes": "中大型豪华SUV，雷神之锤大灯，行李架，电动尾门，全景天窗"
  },
  "沃尔沃|v60|2024": {
    "body_style": "wagon",
    "doors": 5,
    "has_sunroof": true,
    "has_roof_rack": true,
    "headlight_layout": "separate",
    "rear_door_type": "tailgate",
    "notes": "中型豪华旅行车，雷神之锤大灯，行李架，电动尾门，全景天窗"
  },
  "凯迪拉克|ct5|2024": {
    "body_style": "sedan",
    "doors": 4,
    "has_sunroof": true,
    "has_roof_rack": false,
    "headlight_layout": "separate",
    "rear_door_type": "trunk_lid",
    "notes": "中型豪华轿车，盾形格栅，直列式大灯，普通天窗"
  },
  "凯迪拉克|ct6|2024": {
    "body_style": "sedan",
    "doors": 4,
    "has_sunroof": true,
    "has_roof_rack": false,
    "headlight_layout": "separate",
    "rear_door_type": "trunk_lid",
    "notes": "中大型豪华轿车，盾形格栅，直列式大灯，分段式全景天窗"
  },
  "凯迪拉克|xt4|2024": {
    "body_style": "suv",
    "doors": 5,
    "has_sunroof": true,
    "has_roof_rack": true,
    "headlight_layout": "separate",
    "rear_door_type": "tailgate",
    "notes": "紧凑型豪华SUV，盾形格栅，直列式大灯，行李架，全景天窗"
  },
  "凯迪拉克|xt5|2024": {
    "body_style": "suv",
    "doors": 5,
    "has_sunroof": true,
    "has_roof_rack": true,
    "headlight_layout": "separate",
    "rear_door_type": "tailgate",
    "notes": "中型豪华SUV，盾形格栅，直列式大灯，行李架，全景天窗"
  },
  "凯迪拉克|xt6|2024": {
    "body_style": "suv",
    "doors": 5,
    "has_sunroof": true,
    "has_roof_rack": true,
    "headlight_layout": "separate",
    "rear_door_type": "tailgate",
    "notes": "中大型豪华SUV，盾形格栅，直列式大灯，行李架，全景天窗"
  },
  "凯迪拉克|lyriq锐歌|2024": {
    "body_style": "suv",
    "doors": 5,
    "has_sunroof": true,
    "has_roof_rack": false,
    "headlight_layout": "separate",
    "rear_door_type": "tailgate",
    "notes": "中大型纯电豪华SUV，黑晶光曜格栅，直列式大灯，全景天幕"
  },
  "林肯|z|2024": {
    "body_style": "sedan",
    "doors": 4,
    "has_sunroof": true,
    "has_roof_rack": false,
    "headlight_layout": "separate",
    "rear_door_type": "trunk_lid",
    "notes": "中型豪华轿车，星辉格栅，贯穿尾灯，普通天窗"
  },
  "林肯|冒险家|2024": {
    "body_style": "suv",
    "doors": 5,
    "has_sunroof": true,
    "has_roof_rack": true,
    "headlight_layout": "separate",
    "rear_door_type": "tailgate",
    "notes": "紧凑型豪华SUV，星辉格栅，行李架，电动尾门，全景天窗"
  },
  "林肯|航海家|2024": {
    "body_style": "suv",
    "doors": 5,
    "has_sunroof": true,
    "has_roof_rack": true,
    "headlight_layout": "separate",
    "rear_door_type": "tailgate",
    "notes": "中型豪华SUV，星辉格栅，行李架，电动尾门，全景天窗"
  },
  "林肯|飞行家|2024": {
    "body_style": "suv",
    "doors": 5,
    "has_sunroof": true,
    "has_roof_rack": true,
    "headlight_layout": "separate",
    "rear_door_type": "tailgate",
    "notes": "中大型豪华SUV，星辉格栅，行李架，电动尾门，全景天窗"
  },
  "捷豹|xel|2024": {
    "body_style": "sedan",
    "doors": 4,
    "has_sunroof": true,
    "has_roof_rack": false,
    "headlight_layout": "separate",
    "rear_door_type": "trunk_lid",
    "notes": "中型豪华轿车，大嘴格栅，J型日行灯，普通天窗"
  },
  "捷豹|xfl|2024": {
    "body_style": "sedan",
    "doors": 4,
    "has_sunroof": true,
    "has_roof_rack": false,
    "headlight_layout": "separate",
    "rear_door_type": "trunk_lid",
    "notes": "中大型豪华轿车，大嘴格栅，J型日行灯，分段式天窗"
  },
  "捷豹|f-pace|2024": {
    "body_style": "suv",
    "doors": 5,
    "has_sunroof": true,
    "has_roof_rack": true,
    "headlight_layout": "separate",
    "rear_door_type": "tailgate",
    "notes": "中型豪华SUV，大嘴格栅，J型日行灯，行李架，全景天窗"
  },
  "路虎|揽胜极光l|2024": {
    "body_style": "suv",
    "doors": 5,
    "has_sunroof": true,
    "has_roof_rack": true,
    "headlight_layout": "separate",
    "rear_door_type": "tailgate",
    "notes": "紧凑型豪华SUV，蚌壳式引擎盖，行李架，电动尾门，全景天窗"
  },
  "路虎|发现运动版|2024": {
    "body_style": "suv",
    "doors": 5,
    "has_sunroof": true,
    "has_roof_rack": true,
    "headlight_layout": "separate",
    "rear_door_type": "tailgate",
    "notes": "中型豪华SUV，蚌壳式引擎盖，行李架，电动尾门，全景天窗"
  },
  "路虎|揽胜|2024": {
    "body_style": "suv",
    "doors": 5,
    "has_sunroof": true,
    "has_roof_rack": true,
    "headlight_layout": "separate",
    "rear_door_type": "tailgate",
    "notes": "大型豪华SUV，蚌壳式引擎盖，行李架，电动尾门，全景天窗"
  },
  "路虎|卫士|2024": {
    "body_style": "suv",
    "doors": 5,
    "has_sunroof": true,
    "has_roof_rack": true,
    "headlight_layout": "round",
    "rear_door_type": "tailgate",
    "notes": "中大型越野SUV，圆灯设计，行李架，侧开尾门，全景天窗"
  },
  "保时捷|macan|2024": {
    "body_style": "suv",
    "doors": 5,
    "has_sunroof": true,
    "has_roof_rack": false,
    "headlight_layout": "separate",
    "rear_door_type": "tailgate",
    "notes": "中型豪华SUV，蛙眼大灯，电动尾门，全景天窗"
  },
  "保时捷|cayenne|2024": {
    "body_style": "suv",
    "doors": 5,
    "has_sunroof": true,
    "has_roof_rack": true,
    "headlight_layout": "separate",
    "rear_door_type": "tailgate",
    "notes": "中大型豪华SUV，蛙眼大灯，行李架，电动尾门，全景天窗"
  },
  "保时捷|panamera|2024": {
    "body_style": "sedan",
    "doors": 4,
    "has_sunroof": true,
    "has_roof_rack": false,
    "headlight_layout": "separate",
    "rear_door_type": "trunk_lid",
    "notes": "大型豪华轿跑，蛙眼大灯，溜背造型，分段式全景天窗"
  },
  "保时捷|taycan|2024": {
    "body_style": "sedan",
    "doors": 4,
    "has_sunroof": true,
    "has_roof_rack": false,
    "headlight_layout": "separate",
    "rear_door_type": "trunk_lid",
    "notes": "中大型纯电轿跑，四点式大灯，溜背造型，全景天幕"
  },
  "保时捷|911|2024": {
    "body_style": "coupe",
    "doors": 2,
    "has_sunroof": true,
    "has_roof_rack": false,
    "headlight_layout": "round",
    "rear_door_type": "trunk_lid",
    "notes": "跑车，经典圆灯，后置引擎，溜背造型，普通天窗"
  },
  "玛莎拉蒂|ghibli|2024": {
    "body_style": "sedan",
    "doors": 4,
    "has_sunroof": true,
    "has_roof_rack": false,
    "headlight_layout": "separate",
    "rear_door_type": "trunk_lid",
    "notes": "中大型豪华轿跑，大嘴格栅，三叉戟徽标，普通天窗"
  },
  "玛莎拉蒂|levante|2024": {
    "body_style": "suv",
    "doors": 5,
    "has_sunroof": true,
    "has_roof_rack": true,
    "headlight_layout": "separate",
    "rear_door_type": "tailgate",
    "notes": "中大型豪华SUV，大嘴格栅，三叉戟徽标，行李架，全景天窗"
  },
  "宾利|飞驰|2024": {
    "body_style": "sedan",
    "doors": 4,
    "has_sunroof": true,
    "has_roof_rack": false,
    "headlight_layout": "round",
    "rear_door_type": "trunk_lid",
    "notes": "大型豪华轿车，圆灯设计，飞翼徽标，分段式全景天窗"
  },
  "宾利|添越|2024": {
    "body_style": "suv",
    "doors": 5,
    "has_sunroof": true,
    "has_roof_rack": true,
    "headlight_layout": "round",
    "rear_door_type": "tailgate",
    "notes": "中大型豪华SUV，圆灯设计，飞翼徽标，行李架，全景天窗"
  },
  "劳斯莱斯|古思特|2024": {
    "body_style": "sedan",
    "doors": 4,
    "has_sunroof": true,
    "has_roof_rack": false,
    "headlight_layout": "separate",
    "rear_door_type": "trunk_lid",
    "notes": "大型豪华轿车，帕特农格栅，欢庆女神，分段式全景天窗"
  },
  "劳斯莱斯|库里南|2024": {
    "body_style": "suv",
    "doors": 5,
    "has_sunroof": true,
    "has_roof_rack": true,
    "headlight_layout": "separate",
    "rear_door_type": "tailgate",
    "notes": "大型豪华SUV，帕特农格栅，欢庆女神，行李架，全景天窗"
  },
  "兰博基尼|urus|2024": {
    "body_style": "suv",
    "doors": 5,
    "has_sunroof": true,
    "has_roof_rack": false,
    "headlight_layout": "separate",
    "rear_door_type": "tailgate",
    "notes": "中大型豪华SUV，Y型日行灯，公牛徽标，电动尾门，全景天窗"
  },
  "法拉利|roma|2024": {
    "body_style": "coupe",
    "doors": 2,
    "has_sunroof": true,
    "has_roof_rack": false,
    "headlight_layout": "separate",
    "rear_door_type": "trunk_lid",
    "notes": "跑车，优雅流线设计，跃马徽标，溜背造型，普通天窗"
  },
  "迈凯伦|artura|2024": {
    "body_style": "coupe",
    "doors": 2,
    "has_sunroof": true,
    "has_roof_rack": false,
    "headlight_layout": "separate",
    "rear_door_type": "trunk_lid",
    "notes": "跑车，蝴蝶门设计，混动超跑，溜背造型，普通天窗"
  },
  "smart|精灵#1|2024": {
    "body_style": "suv",
    "doors": 5,
    "has_sunroof": true,
    "has_roof_rack": false,
    "headlight_layout": "separate",
    "rear_door_type": "tailgate",
    "notes": "小型纯电SUV，圆润造型，贯穿尾灯，全景天幕，电动尾门"
  },
  "smart|精灵#3|2024": {
    "body_style": "suv",
    "doors": 5,
    "has_sunroof": true,
    "has_roof_rack": false,
    "headlight_layout": "separate",
    "rear_door_type": "tailgate",
    "notes": "紧凑型纯电轿跑SUV，圆润造型，溜背设计，贯穿尾灯，全景天幕"
  },
  "mini|cooper|2024": {
    "body_style": "hatchback",
    "doors": 5,
    "has_sunroof": true,
    "has_roof_rack": false,
    "headlight_layout": "round",
    "rear_door_type": "tailgate",
    "notes": "小型豪华两厢车，经典圆灯，电动尾门，全景天窗"
  },
  "mini|countryman|2024": {
    "body_style": "suv",
    "doors": 5,
    "has_sunroof": true,
    "has_roof_rack": true,
    "headlight_layout": "round",
    "rear_door_type": "tailgate",
    "notes": "紧凑型豪华SUV，经典圆灯，行李架，电动尾门，全景天窗"
  },
  "jeep|牧马人|2024": {
    "body_style": "suv",
    "doors": 5,
    "has_sunroof": true,
    "has_roof_rack": true,
    "headlight_layout": "round",
    "rear_door_type": "tailgate",
    "notes": "中型越野SUV，七孔格栅，圆灯设计，可拆卸车顶，行李架"
  },
  "jeep|大切诺基|2024": {
    "body_style": "suv",
    "doors": 5,
    "has_sunroof": true,
    "has_roof_rack": true,
    "headlight_layout": "separate",
    "rear_door_type": "tailgate",
    "notes": "中大型豪华SUV，七孔格栅，行李架，电动尾门，全景天窗"
  },
  "吉利|星瑞|2024": {
    "body_style": "sedan",
    "doors": 4,
    "has_sunroof": true,
    "has_roof_rack": false,
    "headlight_layout": "separate",
    "rear_door_type": "trunk_lid",
    "notes": "紧凑型轿车，能量音弦格栅，普通天窗，家用轿车"
  },
  "吉利|星越l|2024": {
    "body_style": "suv",
    "doors": 5,
    "has_sunroof": true,
    "has_roof_rack": true,
    "headlight_layout": "separate",
    "rear_door_type": "tailgate",
    "notes": "紧凑型SUV，直瀑格栅，行李架，电动尾门，全景天窗"
  },
  "吉利|帝豪|2024": {
    "body_style": "sedan",
    "doors": 4,
    "has_sunroof": false,
    "has_roof_rack": false,
    "headlight_layout": "separate",
    "rear_door_type": "trunk_lid",
    "notes": "紧凑型轿车，水滴涟漪格栅，普通大灯，无天窗，家用代步"
  },
  "吉利|博越l|2024": {
    "body_style": "suv",
    "doors": 5,
    "has_sunroof": true,
    "has_roof_rack": true,
    "headlight_layout": "separate",
    "rear_door_type": "tailgate",
    "notes": "紧凑型SUV，光波涟漪格栅，行李架，电动尾门，全景天窗"
  },
  "吉利|银河l7|2024": {
    "body_style": "suv",
    "doors": 5,
    "has_sunroof": true,
    "has_roof_rack": false,
    "headlight_layout": "贯穿式",
    "rear_door_type": "tailgate",
    "notes": "紧凑型插混SUV，贯穿灯带，电动尾门，全景天幕"
  },
  "吉利|缤越|2024": {
    "body_style": "suv",
    "doors": 5,
    "has_sunroof": true,
    "has_roof_rack": false,
    "headlight_layout": "separate",
    "rear_door_type": "tailgate",
    "notes": "小型SUV，星空回想格栅，电动尾门，普通天窗"
  },
  "极氪|001|2024": {
    "body_style": "wagon",
    "doors": 5,
    "has_sunroof": true,
    "has_roof_rack": false,
    "headlight_layout": "separate",
    "rear_door_type": "tailgate",
    "notes": "中大型纯电猎装车，分体式大灯，电动尾门，全景天幕"
  },
  "极氪|007|2024": {
    "body_style": "sedan",
    "doors": 4,
    "has_sunroof": true,
    "has_roof_rack": false,
    "headlight_layout": "separate",
    "rear_door_type": "trunk_lid",
    "notes": "中型纯电轿车，贯穿灯幕，溜背造型，全景天幕"
  },
  "极氪|009|2024": {
    "body_style": "mpv",
    "doors": 5,
    "has_sunroof": true,
    "has_roof_rack": false,
    "headlight_layout": "separate",
    "rear_door_type": "sliding",
    "notes": "中大型纯电豪华MPV，镀铬格栅，双侧电动滑门，电动尾门，分段式天幕"
  },
  "领克|03|2024": {
    "body_style": "sedan",
    "doors": 4,
    "has_sunroof": true,
    "has_roof_rack": false,
    "headlight_layout": "separate",
    "rear_door_type": "trunk_lid",
    "notes": "紧凑型运动轿车，北极之光日行灯，普通天窗，运动风格"
  },
  "领克|08|2024": {
    "body_style": "suv",
    "doors": 5,
    "has_sunroof": true,
    "has_roof_rack": false,
    "headlight_layout": "separate",
    "rear_door_type": "tailgate",
    "notes": "中型插混SUV，破晓之光日行灯，电动尾门，全景天幕"
  },
  "领克|09|2024": {
    "body_style": "suv",
    "doors": 5,
    "has_sunroof": true,
    "has_roof_rack": true,
    "headlight_layout": "separate",
    "rear_door_type": "tailgate",
    "notes": "中大型插混SUV，直瀑格栅，行李架，电动尾门，全景天窗"
  },
  "领克|06|2024": {
    "body_style": "suv",
    "doors": 5,
    "has_sunroof": true,
    "has_roof_rack": false,
    "headlight_layout": "separate",
    "rear_door_type": "tailgate",
    "notes": "小型SUV，北极之光日行灯，电动尾门，普通天窗"
  },
  "长安|cs75 plus|2024": {
    "body_style": "suv",
    "doors": 5,
    "has_sunroof": true,
    "has_roof_rack": true,
    "headlight_layout": "贯穿式",
    "rear_door_type": "tailgate",
    "notes": "紧凑型SUV，无边界格栅，行李架，电动尾门，全景天窗"
  },
  "长安|cs55 plus|2024": {
    "body_style": "suv",
    "doors": 5,
    "has_sunroof": true,
    "has_roof_rack": false,
    "headlight_layout": "separate",
    "rear_door_type": "tailgate",
    "notes": "紧凑型SUV，无边界格栅，电动尾门，普通天窗"
  },
  "长安|逸动|2024": {
    "body_style": "sedan",
    "doors": 4,
    "has_sunroof": true,
    "has_roof_rack": false,
    "headlight_layout": "separate",
    "rear_door_type": "trunk_lid",
    "notes": "紧凑型轿车，无边界格栅，普通天窗，家用轿车"
  },
  "长安|uni-v|2024": {
    "body_style": "sedan",
    "doors": 4,
    "has_sunroof": true,
    "has_roof_rack": false,
    "headlight_layout": "separate",
    "rear_door_type": "trunk_lid",
    "notes": "紧凑型轿跑，无边界格栅，电动尾翼，普通天窗，运动风格"
  },
  "长安|uni-k|2024": {
    "body_style": "suv",
    "doors": 5,
    "has_sunroof": true,
    "has_roof_rack": false,
    "headlight_layout": "separate",
    "rear_door_type": "tailgate",
    "notes": "中型SUV，无边界格栅，电动尾门，全景天窗"
  },
  "长安|深蓝sl03|2024": {
    "body_style": "sedan",
    "doors": 4,
    "has_sunroof": true,
    "has_roof_rack": false,
    "headlight_layout": "separate",
    "rear_door_type": "trunk_lid",
    "notes": "中型纯电/增程轿车，星能之瓣大灯，溜背造型，全景天幕"
  },
  "长安|深蓝s07|2024": {
    "body_style": "suv",
    "doors": 5,
    "has_sunroof": true,
    "has_roof_rack": false,
    "headlight_layout": "separate",
    "rear_door_type": "tailgate",
    "notes": "中型纯电/增程SUV，星能之瓣大灯，电动尾门，全景天幕"
  },
  "长安|阿维塔11|2024": {
    "body_style": "suv",
    "doors": 5,
    "has_sunroof": true,
    "has_roof_rack": false,
    "headlight_layout": "separate",
    "rear_door_type": "tailgate",
    "notes": "中大型纯电SUV，碟翼式前脸，电动尾门，全景天幕，华为智驾"
  },
  "长安|阿维塔12|2024": {
    "body_style": "sedan",
    "doors": 4,
    "has_sunroof": true,
    "has_roof_rack": false,
    "headlight_layout": "separate",
    "rear_door_type": "trunk_lid",
    "notes": "中大型纯电轿车，碟翼式前脸，溜背造型，全景天幕，华为智驾"
  },
  "长城|哈弗h6|2024": {
    "body_style": "suv",
    "doors": 5,
    "has_sunroof": true,
    "has_roof_rack": true,
    "headlight_layout": "separate",
    "rear_door_type": "tailgate",
    "notes": "紧凑型SUV，星轨格栅，行李架，电动尾门，全景天窗"
  },
  "长城|哈弗大狗|2024": {
    "body_style": "suv",
    "doors": 5,
    "has_sunroof": true,
    "has_roof_rack": true,
    "headlight_layout": "round",
    "rear_door_type": "tailgate",
    "notes": "紧凑型SUV，复古圆灯，行李架，电动尾门，全景天窗"
  },
  "长城|坦克300|2024": {
    "body_style": "suv",
    "doors": 5,
    "has_sunroof": true,
    "has_roof_rack": true,
    "headlight_layout": "round",
    "rear_door_type": "tailgate",
    "notes": "紧凑型越野SUV，复古圆灯，硬派方盒子，行李架，侧开尾门"
  },
  "长城|坦克500|2024": {
    "body_style": "suv",
    "doors": 5,
    "has_sunroof": true,
    "has_roof_rack": true,
    "headlight_layout": "separate",
    "rear_door_type": "tailgate",
    "notes": "中大型越野SUV，粗壮镀铬格栅，行李架，电动尾门，全景天窗"
  },
  "长城|魏牌蓝山|2024": {
    "body_style": "suv",
    "doors": 5,
    "has_sunroof": true,
    "has_roof_rack": false,
    "headlight_layout": "separate",
    "rear_door_type": "tailgate",
    "notes": "中大型六座SUV，梯形格栅，电动尾门，全景天窗"
  },
  "长城|欧拉好猫|2024": {
    "body_style": "hatchback",
    "doors": 5,
    "has_sunroof": true,
    "has_roof_rack": false,
    "headlight_layout": "round",
    "rear_door_type": "tailgate",
    "notes": "小型纯电两厢车，复古圆灯，圆润造型，电动尾门，普通天窗"
  },
  "长城|长城炮|2024": {
    "body_style": "pickup",
    "doors": 4,
    "has_sunroof": true,
    "has_roof_rack": false,
    "headlight_layout": "separate",
    "rear_door_type": "tailgate",
    "notes": "中大型皮卡，粗壮格栅，货箱尾门，普通天窗"
  },
  "奇瑞|瑞虎8|2024": {
    "body_style": "suv",
    "doors": 5,
    "has_sunroof": true,
    "has_roof_rack": true,
    "headlight_layout": "separate",
    "rear_door_type": "tailgate",
    "notes": "中型七座SUV，虎啸格栅，行李架，电动尾门，全景天窗"
  },
  "奇瑞|瑞虎9|2024": {
    "body_style": "suv",
    "doors": 5,
    "has_sunroof": true,
    "has_roof_rack": true,
    "headlight_layout": "separate",
    "rear_door_type": "tailgate",
    "notes": "中大型SUV，直瀑格栅，行李架，电动尾门，全景天窗"
  },
  "奇瑞|艾瑞泽8|2024": {
    "body_style": "sedan",
    "doors": 4,
    "has_sunroof": true,
    "has_roof_rack": false,
    "headlight_layout": "separate",
    "rear_door_type": "trunk_lid",
    "notes": "紧凑型轿车，纺锤格栅，普通天窗，家用轿车"
  },
  "奇瑞|捷途旅行者|2024": {
    "body_style": "suv",
    "doors": 5,
    "has_sunroof": true,
    "has_roof_rack": true,
    "headlight_layout": "separate",
    "rear_door_type": "tailgate",
    "notes": "紧凑型越野SUV，硬派方盒子，行李架，电动尾门，全景天窗"
  },
  "奇瑞|星纪元et|2024": {
    "body_style": "suv",
    "doors": 5,
    "has_sunroof": true,
    "has_roof_rack": false,
    "headlight_layout": "贯穿式",
    "rear_door_type": "tailgate",
    "notes": "中大型纯电SUV，贯穿灯带，电动尾门，全景天幕"
  },
  "红旗|h5|2024": {
    "body_style": "sedan",
    "doors": 4,
    "has_sunroof": true,
    "has_roof_rack": false,
    "headlight_layout": "separate",
    "rear_door_type": "trunk_lid",
    "notes": "中型豪华轿车，直瀑格栅，红旗立标，普通天窗"
  },
  "红旗|h9|2024": {
    "body_style": "sedan",
    "doors": 4,
    "has_sunroof": true,
    "has_roof_rack": false,
    "headlight_layout": "separate",
    "rear_door_type": "trunk_lid",
    "notes": "中大型豪华轿车，直瀑格栅，红旗立标，分段式全景天窗"
  },
  "红旗|e-qm5|2024": {
    "body_style": "sedan",
    "doors": 4,
    "has_sunroof": true,
    "has_roof_rack": false,
    "headlight_layout": "separate",
    "rear_door_type": "trunk_lid",
    "notes": "中型纯电轿车，直瀑格栅，红旗立标，全景天幕"
  },
  "红旗|hs5|2024": {
    "body_style": "suv",
    "doors": 5,
    "has_sunroof": true,
    "has_roof_rack": true,
    "headlight_layout": "separate",
    "rear_door_type": "tailgate",
    "notes": "中型豪华SUV，直瀑格栅，红旗立标，行李架，全景天窗"
  },
  "传祺|m8|2024": {
    "body_style": "mpv",
    "doors": 5,
    "has_sunroof": true,
    "has_roof_rack": false,
    "headlight_layout": "separate",
    "rear_door_type": "sliding",
    "notes": "中大型MPV，醒狮前脸，双侧电动滑门，电动尾门，分段式天窗"
  },
  "传祺|m6|2024": {
    "body_style": "mpv",
    "doors": 5,
    "has_sunroof": true,
    "has_roof_rack": false,
    "headlight_layout": "separate",
    "rear_door_type": "tailgate",
    "notes": "紧凑型MPV，展翼格栅，电动尾门，普通天窗"
  },
  "传祺|gs8|2024": {
    "body_style": "suv",
    "doors": 5,
    "has_sunroof": true,
    "has_roof_rack": true,
    "headlight_layout": "separate",
    "rear_door_type": "tailgate",
    "notes": "中型七座SUV，龙鳞翼格栅，行李架，电动尾门，全景天窗"
  },
  "传祺|影豹|2024": {
    "body_style": "sedan",
    "doors": 4,
    "has_sunroof": true,
    "has_roof_rack": false,
    "headlight_layout": "separate",
    "rear_door_type": "trunk_lid",
    "notes": "紧凑型运动轿车，战机前脸，普通天窗，运动风格"
  },
  "北汽|eu5|2024": {
    "body_style": "sedan",
    "doors": 4,
    "has_sunroof": false,
    "has_roof_rack": false,
    "headlight_layout": "separate",
    "rear_door_type": "trunk_lid",
    "notes": "紧凑型纯电轿车，封闭式格栅，普通大灯，无天窗"
  },
  "北汽|魔方|2024": {
    "body_style": "suv",
    "doors": 5,
    "has_sunroof": true,
    "has_roof_rack": false,
    "headlight_layout": "separate",
    "rear_door_type": "tailgate",
    "notes": "紧凑型SUV，无边界格栅，电动尾门，普通天窗"
  },
  "名爵|mg7|2024": {
    "body_style": "sedan",
    "doors": 4,
    "has_sunroof": true,
    "has_roof_rack": false,
    "headlight_layout": "separate",
    "rear_door_type": "trunk_lid",
    "notes": "中型轿跑，大嘴格栅，无框车门，电动尾翼，普通天窗"
  },
  "名爵|mg4|2024": {
    "body_style": "hatchback",
    "doors": 5,
    "has_sunroof": true,
    "has_roof_rack": false,
    "headlight_layout": "separate",
    "rear_door_type": "tailgate",
    "notes": "紧凑型纯电两厢车，X型前脸，电动尾门，普通天窗"
  },
  "名爵|mg zs|2024": {
    "body_style": "suv",
    "doors": 5,
    "has_sunroof": true,
    "has_roof_rack": true,
    "headlight_layout": "separate",
    "rear_door_type": "tailgate",
    "notes": "小型SUV，星辉格栅，行李架，电动尾门，普通天窗"
  },
  "荣威|rx5|2024": {
    "body_style": "suv",
    "doors": 5,
    "has_sunroof": true,
    "has_roof_rack": true,
    "headlight_layout": "separate",
    "rear_door_type": "tailgate",
    "notes": "紧凑型SUV，凤羽格栅，行李架，电动尾门，全景天窗"
  },
  "荣威|i5|2024": {
    "body_style": "sedan",
    "doors": 4,
    "has_sunroof": false,
    "has_roof_rack": false,
    "headlight_layout": "separate",
    "rear_door_type": "trunk_lid",
    "notes": "紧凑型轿车，荣麟格栅，普通大灯，无天窗，家用代步"
  },
  "荣威|d7|2024": {
    "body_style": "sedan",
    "doors": 4,
    "has_sunroof": true,
    "has_roof_rack": false,
    "headlight_layout": "separate",
    "rear_door_type": "trunk_lid",
    "notes": "中型纯电/插混轿车，电感化前脸，全景天幕，家用轿车"
  },
  "哪吒|哪吒s|2024": {
    "body_style": "sedan",
    "doors": 4,
    "has_sunroof": true,
    "has_roof_rack": false,
    "headlight_layout": "separate",
    "rear_door_type": "trunk_lid",
    "notes": "中大型纯电/增程轿跑，展翼式前脸，溜背造型，全景天幕"
  },
  "哪吒|哪吒l|2024": {
    "body_style": "suv",
    "doors": 5,
    "has_sunroof": true,
    "has_roof_rack": false,
    "headlight_layout": "separate",
    "rear_door_type": "tailgate",
    "notes": "中型纯电/增程SUV，展翼式前脸，电动尾门，全景天幕"
  },
  "哪吒|哪吒gt|2024": {
    "body_style": "coupe",
    "doors": 2,
    "has_sunroof": true,
    "has_roof_rack": false,
    "headlight_layout": "separate",
    "rear_door_type": "trunk_lid",
    "notes": "双门纯电跑车，展翼式前脸，无框车门，溜背造型，全景天幕"
  },
  "零跑|c11|2024": {
    "body_style": "suv",
    "doors": 5,
    "has_sunroof": true,
    "has_roof_rack": false,
    "headlight_layout": "贯穿式",
    "rear_door_type": "tailgate",
    "notes": "中型纯电/增程SUV，贯穿灯带，电动尾门，全景天幕"
  },
  "零跑|c10|2024": {
    "body_style": "suv",
    "doors": 5,
    "has_sunroof": true,
    "has_roof_rack": false,
    "headlight_layout": "贯穿式",
    "rear_door_type": "tailgate",
    "notes": "中型纯电/增程SUV，贯穿灯带，电动尾门，全景天幕"
  },
  "零跑|t03|2024": {
    "body_style": "hatchback",
    "doors": 5,
    "has_sunroof": false,
    "has_roof_rack": false,
    "headlight_layout": "separate",
    "rear_door_type": "tailgate",
    "notes": "微型纯电两厢车，圆润造型，无天窗，电动尾门，代步小车"
  },
  "零跑|c16|2024": {
    "body_style": "suv",
    "doors": 5,
    "has_sunroof": true,
    "has_roof_rack": false,
    "headlight_layout": "贯穿式",
    "rear_door_type": "tailgate",
    "notes": "中大型六座纯电/增程SUV，贯穿灯带，电动尾门，全景天幕"
  },
  "岚图|free|2024": {
    "body_style": "suv",
    "doors": 5,
    "has_sunroof": true,
    "has_roof_rack": false,
    "headlight_layout": "贯穿式",
    "rear_door_type": "tailgate",
    "notes": "中大型增程/纯电SUV，贯穿灯带，电动尾门，可升降全景天幕"
  },
  "岚图|梦想家|2024": {
    "body_style": "mpv",
    "doors": 5,
    "has_sunroof": true,
    "has_roof_rack": false,
    "headlight_layout": "贯穿式",
    "rear_door_type": "sliding",
    "notes": "中大型豪华MPV，贯穿灯带，双侧电动滑门，电动尾门，分段式天幕"
  },
  "岚图|追光|2024": {
    "body_style": "sedan",
    "doors": 4,
    "has_sunroof": true,
    "has_roof_rack": false,
    "headlight_layout": "贯穿式",
    "rear_door_type": "trunk_lid",
    "notes": "中大型纯电轿车，贯穿灯带，溜背造型，全景天幕"
  },
  "智己|l7|2024": {
    "body_style": "sedan",
    "doors": 4,
    "has_sunroof": true,
    "has_roof_rack": false,
    "headlight_layout": "separate",
    "rear_door_type": "trunk_lid",
    "notes": "中大型纯电轿车，Sigma前脸，可编程大灯，全景天幕"
  },
  "智己|ls6|2024": {
    "body_style": "suv",
    "doors": 5,
    "has_sunroof": true,
    "has_roof_rack": false,
    "headlight_layout": "separate",
    "rear_door_type": "tailgate",
    "notes": "中大型纯电轿跑SUV，Sigma前脸，电动尾门，全景天幕"
  },
  "智己|ls7|2024": {
    "body_style": "suv",
    "doors": 5,
    "has_sunroof": true,
    "has_roof_rack": false,
    "headlight_layout": "separate",
    "rear_door_type": "tailgate",
    "notes": "中大型纯电SUV，Sigma前脸，电动尾门，前穹顶玻璃"
  },
  "问界|m5|2024": {
    "body_style": "suv",
    "doors": 5,
    "has_sunroof": true,
    "has_roof_rack": false,
    "headlight_layout": "separate",
    "rear_door_type": "tailgate",
    "notes": "中型增程/纯电SUV，梯形格栅，电动尾门，全景天幕，华为智驾"
  },
  "问界|m7|2024": {
    "body_style": "suv",
    "doors": 5,
    "has_sunroof": true,
    "has_roof_rack": false,
    "headlight_layout": "separate",
    "rear_door_type": "tailgate",
    "notes": "中大型增程SUV，梯形格栅，电动尾门，全景天幕，华为智驾"
  },
  "问界|m9|2024": {
    "body_style": "suv",
    "doors": 5,
    "has_sunroof": true,
    "has_roof_rack": false,
    "headlight_layout": "贯穿式",
    "rear_door_type": "tailgate",
    "notes": "大型豪华增程/纯电SUV，贯穿灯带，电动尾门，全景天幕，华为智驾"
  },
  "小米|su7|2024": {
    "body_style": "sedan",
    "doors": 4,
    "has_sunroof": true,
    "has_roof_rack": false,
    "headlight_layout": "separate",
    "rear_door_type": "trunk_lid",
    "notes": "中大型纯电轿跑，水滴大灯，溜背造型，全景天幕，运动风格"
  },
  "极狐|阿尔法s|2024": {
    "body_style": "sedan",
    "doors": 4,
    "has_sunroof": true,
    "has_roof_rack": false,
    "headlight_layout": "separate",
    "rear_door_type": "trunk_lid",
    "notes": "中大型纯电轿车，X型前脸，溜背造型，全景天幕"
  },
  "极狐|阿尔法t|2024": {
    "body_style": "suv",
    "doors": 5,
    "has_sunroof": true,
    "has_roof_rack": false,
    "headlight_layout": "separate",
    "rear_door_type": "tailgate",
    "notes": "中型纯电SUV，X型前脸，电动尾门，全景天幕"
  },
  "五菱|宏光miniev|2024": {
    "body_style": "hatchback",
    "doors": 3,
    "has_sunroof": false,
    "has_roof_rack": false,
    "headlight_layout": "separate",
    "rear_door_type": "tailgate",
    "notes": "微型纯电两厢车，方盒子造型，双门四座，无天窗，入门级代步车"
  },
  "五菱|五菱荣光|2024": {
    "body_style": "van",
    "doors": 5,
    "has_sunroof": false,
    "has_roof_rack": false,
    "headlight_layout": "separate",
    "rear_door_type": "tailgate",
    "notes": "微型面包车，实用造型，无天窗，侧滑门+对开尾门"
  },
  "五菱|五菱宏光|2024": {
    "body_style": "van",
    "doors": 5,
    "has_sunroof": false,
    "has_roof_rack": false,
    "headlight_layout": "separate",
    "rear_door_type": "tailgate",
    "notes": "紧凑型MPV/面包车，实用造型，无天窗，侧滑门+上掀尾门"
  },
  "长安|长安之星|2024": {
    "body_style": "van",
    "doors": 5,
    "has_sunroof": false,
    "has_roof_rack": false,
    "headlight_layout": "separate",
    "rear_door_type": "tailgate",
    "notes": "微型面包车，实用造型，无天窗，侧滑门+对开尾门"
  }
}